setup.cfg
setup.py
pyIGTLink/__init__.py
pyIGTLink/pyIGTLink.py
pyIGTLink/tests.py
pyIGTLink.egg-info/PKG-INFO
pyIGTLink.egg-info/SOURCES.txt
pyIGTLink.egg-info/dependency_links.txt
pyIGTLink.egg-info/requires.txt
pyIGTLink.egg-info/top_level.txt