Metadata-Version: 1.0
Name: pyIGTLink
Version: 0.2.1
Summary: python interface for OpenIGTLink
Home-page: https://github.com/Danielhiversen/pyIGTLink
Author: Daniel Hoyer Iversen
Author-email: UNKNOWN
License: UNKNOWN
Platform: UNKNOWN
